scrapy_proxy_validation/__init__.py
scrapy_proxy_validation/_version.py
scrapy_proxy_validation/downloadermiddlewares/__init__.py
scrapy_proxy_validation/downloadermiddlewares/proxy_validation.py
scrapy_proxy_validation/settings/__init__.py
scrapy_proxy_validation/settings/default_settings.py
scrapy_proxy_validation/utils/__init__.py
scrapy_proxy_validation/utils/recycle_request.py
scrapy_proxy_validation-0.0.4.dist-info/DESCRIPTION.rst
scrapy_proxy_validation-0.0.4.dist-info/METADATA
scrapy_proxy_validation-0.0.4.dist-info/RECORD
scrapy_proxy_validation-0.0.4.dist-info/WHEEL
scrapy_proxy_validation-0.0.4.dist-info/metadata.json
scrapy_proxy_validation-0.0.4.dist-info/top_level.txt
