Metadata-Version: 2.0
Name: scrapy-proxy-validation
Version: 0.0.4
Summary: UNKNOWN
Home-page: https://github.com/grammy-jiang/scrapy-proxy-validation
Author: Grammy Jiang
Author-email: grammy.jiang@gmail.com
License: BSD
Platform: UNKNOWN
Classifier: Framework :: Scrapy
Classifier: Development Status :: 2 - Pre-Alpha
Classifier: Environment :: Plugins
Classifier: Intended Audience :: Developers
Classifier: License :: OSI Approved :: BSD License
Classifier: Operating System :: OS Independent
Classifier: Programming Language :: Python
Classifier: Programming Language :: Python :: 3
Classifier: Programming Language :: Python :: 3.5
Classifier: Programming Language :: Python :: 3.6
Classifier: Topic :: Internet :: WWW/HTTP
Classifier: Topic :: Software Development :: Libraries :: Python Modules
Requires-Dist: txmongo
Requires-Dist: scrapy (>=1.4.0)
